TemasClaros/__init__.py
TemasClaros/alabaster.py
TemasClaros/ashes_light.py
TemasClaros/atom_one_light.py
TemasClaros/ayu_light.py
TemasClaros/catppuccin_latte.py
TemasClaros/enfocado_light.py
TemasClaros/everforest_light.py
TemasClaros/github_light.py
TemasClaros/github_light_colorblind.py
TemasClaros/github_light_default.py
TemasClaros/github_light_high_contrast.py
TemasClaros/github_light_tritanopia.py
TemasClaros/gruvbox_light.py
TemasClaros/gruvbox_material_hard_light.py
TemasClaros/gruvbox_material_medium_light.py
TemasClaros/high_contrast.py
TemasClaros/msx.py
TemasClaros/night_owlish_light.py
TemasClaros/noctis_lux.py
TemasClaros/nord_light.py
TemasClaros/papercolor_light.py
TemasClaros/papertheme.py
TemasClaros/pencil_light.py
TemasClaros/rose_pine_dawn.py
TemasClaros/solarized_light.py
TemasOscuros/Cobalt2.py
TemasOscuros/Mariana.py
TemasOscuros/__init__.py
TemasOscuros/afterglow.py
TemasOscuros/alacritty_0_12.py
TemasOscuros/ashes_dark.py
TemasOscuros/base16_default_dark.py
TemasOscuros/bluish.py
TemasOscuros/breeze.py
TemasOscuros/catppuccin_frappe.py
TemasOscuros/catppuccin_macchiato.py
TemasOscuros/catppuccin_mocha.py
TemasOscuros/chicago95.py
TemasOscuros/citylights.py
TemasOscuros/dark_pastels.py
TemasOscuros/deep_space.py
TemasOscuros/doom_one.py
TemasOscuros/dracula_plus.py
TemasOscuros/enfocado_dark.py
TemasOscuros/everforest_dark.py
TemasOscuros/falcon.py
TemasOscuros/flat_remix.py
TemasOscuros/flexoki.py
TemasOscuros/github_dark.py
TemasOscuros/github_dark_dimmed.py
TemasOscuros/gnome_terminal.py
TemasOscuros/google.py
TemasOscuros/gruvbox_dark.py
TemasOscuros/gruvbox_material.py
TemasOscuros/gruvbox_material_hard_dark.py
TemasOscuros/gruvbox_material_medium_dark.py
TemasOscuros/hardhacker.py
TemasOscuros/hatsunemiku.py
TemasOscuros/horizon_dark.py
TemasOscuros/inferno.py
TemasOscuros/iris.py
TemasOscuros/kanagawa_dragon.py
TemasOscuros/kanagawa_wave.py
TemasOscuros/konsole_linux.py
TemasOscuros/low_contrast.py
TemasOscuros/marine_dark.py
pycrypy-1.0.5.dist-info/LICENSE.es.md
pycrypy-1.0.5.dist-info/LICENSE.md
pycrypy-1.0.5.dist-info/METADATA
pycrypy-1.0.5.dist-info/WHEEL
pycrypy-1.0.5.dist-info/entry_points.txt
pycrypy-1.0.5.dist-info/top_level.txt
pycrypy-1.0.5.dist-info/RECORD
