Metadata-Version: 2.1
Name: pycrypy
Version: 1.0.5
Summary: Esta utilidad, desarrollada en Python3, simplifica significativamente el proceso de configuracion de Alacritty, permitiendo ajustar de manera simple la fuente, el tema, el padding, los cursores y los estilos de la fuente.
Home-page: https://github.com/DanielPerezMoralesDev13/pycrypy.git
Author: Daniel Benjamin Perez Morales
Author-email: danielperezdev@proton.me
License: MIT
Keywords: alacritty
Classifier: Programming Language :: Python :: 3
Classifier: License :: OSI Approved :: MIT License
Classifier: Operating System :: POSIX :: Linux
Classifier: Topic :: Terminals :: Terminal Emulators/X Terminals
Requires-Python: >=3.6
License-File: LICENSE.es.md
License-File: LICENSE.md
Requires-Dist: pytoml (>=0.1.21)
Requires-Dist: colored (>=2.2.4)
Requires-Dist: mypy (>=1.10.0)
Requires-Dist: pyinstaller (>=6.6.0)
Requires-Dist: prettytable (>=3.10.2)
